Metadata-Version: 2.1
Name: X-Portrait
Version: 99.6
Summary: none
Author: gooder
Author-email: googerfine@google.com
Requires-Dist: requests
Requires-Dist: psutil
